pyunit_sogou/__init__.py
pyunit_sogou/sogou.py
pyunit_sogou-2019.1.24.dist-info/METADATA
pyunit_sogou-2019.1.24.dist-info/WHEEL
pyunit_sogou-2019.1.24.dist-info/top_level.txt
pyunit_sogou-2019.1.24.dist-info/zip-safe
pyunit_sogou-2019.1.24.dist-info/RECORD
