Metadata-Version: 2.1
Name: pyunit-sogou
Version: 2019.1.24
Summary: 搜狗词库专业下载模块
Home-page: https://github.com/PyUnit/pyunit-sogou
Author: Jtyoui
Author-email: jtyoui@qq.com
License: MIT Licence
Platform: any
Classifier: Programming Language :: Python :: 3
Classifier: License :: OSI Approved :: MIT License
Classifier: Operating System :: OS Independent
Requires-Dist: certifi (==2019.11.28)
Requires-Dist: chardet (==3.0.4)
Requires-Dist: fake-useragent (==0.1.11)
Requires-Dist: idna (==2.8)
Requires-Dist: requests (==2.22.0)
Requires-Dist: urllib3 (==1.25.8)
